Metadata-Version: 2.1
Name: lifton
Version: 1.0.5
Summary: Combining DNA and protein alignments to improve genome annotation with LiftOn
Home-page: https://github.com/Kuanhao-Chao/Lifton
Author: Kuan-Hao Chao
Author-email: kh.chao@cs.jhu.edu
Requires-Python: >=3.6
License-File: LICENSE
Requires-Dist: numpy>=1.22.0
Requires-Dist: biopython>=1.76
Requires-Dist: cigar>=0.1.3
Requires-Dist: parasail>=1.2.4
Requires-Dist: intervaltree>=3.1.0
Requires-Dist: interlap>=0.2.6
Requires-Dist: networkx>=3.3
Requires-Dist: pyfaidx>=0.5.8
Requires-Dist: pysam>=0.19.1
Requires-Dist: gffutils>=0.10.1
Requires-Dist: ujson>=3.2.0
Requires-Dist: pytest>=7.0.0
